data/__init__.py
data/data.py
data/eeg.py
data/japan.py
data/jura.py
sgpvae/__init__.py
sgpvae/kernels/__init__.py
sgpvae/kernels/composition.py
sgpvae/kernels/kernels.py
sgpvae/likelihoods/__init__.py
sgpvae/likelihoods/base.py
sgpvae/likelihoods/bernoulli.py
sgpvae/likelihoods/gaussian.py
sgpvae/likelihoods/gprn.py
sgpvae/likelihoods/networks.py
sgpvae/likelihoods/partial_gaussian.py
sgpvae/models/__init__.py
sgpvae/models/base.py
sgpvae/models/gpvae.py
sgpvae/utils/__init__.py
sgpvae/utils/dataset.py
sgpvae/utils/matrix.py
sgpvae/utils/metric.py
sgpvae/utils/misc.py
sgpvae/utils/training.py
sgpvae/utils/transforms.py
sgpvae-0.1.dist-info/METADATA
sgpvae-0.1.dist-info/WHEEL
sgpvae-0.1.dist-info/top_level.txt
sgpvae-0.1.dist-info/RECORD
