Metadata-Version: 2.1
Name: sgpvae
Version: 0.1
Summary: Sparse Gaussian process variational autoencoders
Home-page: https://github.com/MattAshman/sgpvae
Author: Matthew Ashman
Author-email: mca39@cam.ac.uk
License: UNKNOWN
Platform: UNKNOWN
Classifier: Programming Language :: Python :: 3
Classifier: License :: OSI Approved :: MIT License
Classifier: Operating System :: OS Independent
Requires-Python: >3.6
